eco_num_extract/__init__.py
eco_num_extract/main.py
eco_num_extract/prompts.py
eco_num_extract-2025.12.22085323.dist-info/METADATA
eco_num_extract-2025.12.22085323.dist-info/WHEEL
eco_num_extract-2025.12.22085323.dist-info/top_level.txt
eco_num_extract-2025.12.22085323.dist-info/RECORD
