Metadata-Version: 2.4
Name: eco-num-extract
Version: 2025.12.22085323
Summary: eco-num-extract turns natural science text into structured numeric data using llmatch-guided outputs.
Author-email: eco-num-extract <hi@eugene.plus>
License: MIT
Project-URL: Homepage, https://github.com/chigwell/eco-num-extract
Requires-Python: >=3.9
Requires-Dist: langchain-llm7>=0.0.0
Requires-Dist: llmatch-messages>=0.0.0
Requires-Dist: langchain-core>=0.3.0
